Metadata-Version: 2.1
Name: WhatsaPy
Version: 0.0.1
Summary: Unofficial python Wrapper for Whatsapp Businness API.
Home-page: https://github.com/rahulps100/WhatsAppPy
Author: Rahul P S
Author-email: rahulps1000@gmail.com
License: GPLv3
Keywords: whatsapp api python businnes cloud unoffcial
Requires-Python: ~=3.7
License-File: LICENSE.txt
